README.txt
setup.py
van/__init__.py
van.contactology.egg-info/PKG-INFO
van.contactology.egg-info/SOURCES.txt
van.contactology.egg-info/dependency_links.txt
van.contactology.egg-info/namespace_packages.txt
van.contactology.egg-info/not-zip-safe
van.contactology.egg-info/requires.txt
van.contactology.egg-info/top_level.txt
van/contactology/__init__.py
van/contactology/tests/__init__.py
van/contactology/tests/test_contactology.py