Metadata-Version: 1.0
Name: van.contactology
Version: 1.0
Summary: Contactology API for Twisted
Home-page: UNKNOWN
Author: UNKNOWN
Author-email: brian@vanguardistas.net
License: UNKNOWN
Platform: UNKNOWN
